Metadata-Version: 2.1
Name: tkthread
Version: 0.5.1
Summary: Easy multithreading with Tkinter
Home-page: http://github.com/serwy/tkthread
Author: Roger D. Serwy
Author-email: roger.serwy@gmail.com
License: Apache Version 2.0
Keywords: tkinter threading
Platform: Windows
Platform: Linux
Platform: Solaris
Platform: Mac OS-X
Platform: Unix
Classifier: Development Status :: 4 - Beta
Classifier: Intended Audience :: Developers
Classifier: License :: OSI Approved :: Apache Software License
Classifier: Operating System :: OS Independent
Classifier: Programming Language :: Python :: 2.7
Classifier: Programming Language :: Python :: 3
Classifier: Programming Language :: Python :: Implementation :: CPython
Classifier: Programming Language :: Python :: Implementation :: PyPy
Classifier: Topic :: Software Development :: User Interfaces
License-File: LICENSE
